{"lastBuildDate": "Thu, 23 Mar 2023 16:29:44 +0900", "total": 358, "start": 1, "display": 100, "items": [{"title": "\uc11c\uac15 \uce58\uc988\ud63c\ud569<b>\ubd84\ub9d0 1kg</b> <b>\ud669\uce58\uc988\ubd84\ub9d0</b> \uac00\ub8e8", "link": "https://search.shopping.naver.com/gate.nhn?id=11519943711", "image": "https://shopping-phinf.pstatic.net/main_1151994/11519943711.1.jpg", "lprice": "12200", "hprice": "", "mallName": "\uc9c4\ubcf4\ub78c\ubab0", "productId": "11519943711", "productType": "2", "brand": "", "maker": "", "category1": "\uc2dd\ud488", "category2": "\uac00\ub8e8/\ubd84\ub9d0\ub958", "category3": "\uae30\ud0c0\ubd84\ub9d0\uac00\ub8e8", "category4": ""}, {"title": "\uaf2c\ubbf8\ub2e4 <b>\ud669\uce58\uc988\ubd84\ub9d0 1kg</b> \uce58\uc988 \ud63c\ud569\ubd84\ub9d0 \ud669\uce58\uc988\uac00\ub8e8", "link": "https://search.shopping.naver.com/gate.nhn?id=83009870917", "image": "https://shopping-phinf.pstatic.net/main_8300987/83009870917.4.jpg", "lprice": "13000", "hprice": "", "mallName": "\ucf54\ucf54\ubca0\uc774\ud0b9", "productId": "83009870917", "productType": "2", "brand": "", "maker": "", "category1": "\uc2dd\ud488", "category2": "\uac00\ub8e8/\ubd84\ub9d0\ub958", "category3": "\uae30\ud0c0\ubd84\ub9d0\uac00\ub8e8", "category4": ""}, {"title": "\uc11c\uac15 <b>\ud669\uce58\uc988\ubd84\ub9d0 1kg</b>", "link": "https://search.shopping.naver.com/gate.nhn?id=29201606102", "image": "https://shopping-phinf.pstatic.net/main_2920160/29201606102.jpg", "lprice": "11900", "hprice": "", "mallName": "\ub9d8\ucfe0\ud0b9", "productId": "29201606102", "productType": "2", "brand": "\uc11c\uac15", "maker": "\uc11c\uac15", "category1": "\uc2dd\ud488", "category2": "\uac00\ub8e8/\ubd84\ub9d0\ub958", "category3": "\uae30\ud0c0\ubd84\ub9d0\uac00\ub8e8", "category4": ""}, {"title": "[\ubc30\uc1a1\ube44\ubcc4\ub3c4/5A-6]\uc11c\uac15 <b>\ud669\uce58\uc988\ubd84\ub9d0</b>\uac00\ub8e8 <b>1kg</b>.", "link": "https://search.shopping.naver.com/gate.nhn?id=30993950974", "image": "https://shopping-phinf.pstatic.net/main_3099395/30993950974.jpg", "lprice": "10900", "hprice": "", "mallName": "\ubca0\uc774\ud0b9\ub9d8", "productId": "30993950974", "productType": "2", "brand": "", "maker": "\uc11c\uac15\uc720\uc5c5", "category1": "\uc2dd\ud488", "category2": "\uac00\ub8e8/\ubd84\ub9d0\ub958", "category3": "\uae30\ud0c0\ubd84\ub9d0\uac00\ub8e8", "category4": ""}, {"title": "\uaf2c\ubbf8\ub2e4 <b>\ud669\uce58\uc988</b>\ud63c\ud569<b>\ubd84\ub9d0 1kg</b> <b>\ud669\uce58\uc988 \ubd84\ub9d0</b> \uac00\ub8e8 \ucf00\uc774\ud06c \ud06c\ub7fc\ube14 \ube75 \ucfe0\ud0a4", "link": "https://search.shopping.naver.com/gate.nhn?id=84406109856", "image": "https://shopping-phinf.pstatic.net/main_8440610/84406109856.jpg", "lprice": "12900", "hprice": "", "mallName": "\ub3c4\uae68\ube44\ubca0\uc774\ud0b9", "productId": "84406109856", "productType": "2", "brand": "", "maker": "", "category1": "\uc2dd\ud488", "category2": "\uac00\ub8e8/\ubd84\ub9d0\ub958", "category3": "\uae30\ud0c0\ubd84\ub9d0\uac00\ub8e8", "category4": ""}, {"title": "<b>\ud669\uce58\uc988 \ubd84\ub9d0 1kg</b> \uac00\ub8e8 \ud63c\ud569 \ud30c\uc6b0\ub354", "link": "https://search.shopping.naver.com/gate.nhn?id=80469566713", "image": "https://shopping-phinf.pstatic.net/main_8046956/80469566713.jpg", "lprice": "13700", "hprice": "", "mallName": "\ud3ec\ubca0\uc774\ucee4", "productId": "80469566713", "productType": "2", "brand": "", "maker": "", "category1": "\uc2dd\ud488", "category2": "\uac00\ub8e8/\ubd84\ub9d0\ub958", "category3": "\uae30\ud0c0\ubd84\ub9d0\uac00\ub8e8", "category4": ""}, {"title": "<b>\ud669\uce58\uc988</b>\ub9db<b>\ubd84\ub9d0 1kg</b> <b>\ud669\uce58\uc988 \ubd84\ub9d0</b> \uac00\ub8e8 \ucfe0\ud0a4 \ucf00\uc774\ud06c \ud06c\ub7fc\ube14 \ube75", "link": "https://search.shopping.naver.com/gate.nhn?id=84316342569", "image": "https://shopping-phinf.pstatic.net/main_8431634/84316342569.jpg", "lprice": "11500", "hprice": "", "mallName": "\ub3c4\uae68\ube44\ubca0\uc774\ud0b9", "productId": "84316342569", "productType": "2", "brand": "", "maker": "", "category1": "\uc2dd\ud488", "category2": "\uac00\ub8e8/\ubd84\ub9d0\ub958", "category3": "\uae30\ud0c0\ubd84\ub9d0\uac00\ub8e8", "category4": ""}, {"title": "<b>\ud669\uce58\uc988\ubd84\ub9d0</b> \uc11c\uac15 \uac00\ub9bc <b>\ud669\uce58\uc988</b>\uac00\ub8e8 <b>\ud669\uce58\uc988</b>\ud30c\uc6b0\ub354 <b>1kg</b>", "link": "https://search.shopping.naver.com/gate.nhn?id=85187449667", "image": "https://shopping-phinf.pstatic.net/main_8518744/85187449667.jpg", "lprice": "12950", "hprice": "", "mallName": "\ubca0\uc774\ud0b9\ud50c\ub7ec\uc2a4", "productId": "85187449667", "productType": "2", "brand": "\uac00\ub9bc", "maker": "\uac00\ub9bc", "category1": "\uc2dd\ud488", "category2": "\uac00\ub8e8/\ubd84\ub9d0\ub958", "category3": "\uae30\ud0c0\ubd84\ub9d0\uac00\ub8e8", "category4": ""}, {"title": "\uc11c\uac15 <b>\ud669\uce58\uc988\ubd84\ub9d0  1kg</b>  1\uac1c", "link": "https://search.shopping.naver.com/gate.nhn?id=31276856231", "image": "https://shopping-phinf.pstatic.net/main_3127685/31276856231.60.jpg", "lprice": "12300", "hprice": "", "mallName": "\ucfe0\ud321", "productId": "31276856231", "productType": "2", "brand": "\uc11c\uac15", "maker": "\uc11c\uac15", "category1": "\uc2dd\ud488", "category2": "\uac00\ub8e8/\ubd84\ub9d0\ub958", "category3": "\uae30\ud0c0\ubd84\ub9d0\uac00\ub8e8", "category4": ""}, {"title": "\uac00\ub9bc <b>\ud669\uce58\uc988</b>\ub9db<b>\ubd84\ub9d01kg</b>", "link": "https://search.shopping.naver.com/gate.nhn?id=85600929780", "image": "https://shopping-phinf.pstatic.net/main_8560092/85600929780.jpg", "lprice": "12500", "hprice": "", "mallName": "\ubca0\uc774\ud0b9\uc2f8\ub2e4\uad6c", "productId": "85600929780", "productType": "2", "brand": "", "maker": "", "category1": "\uc2dd\ud488", "category2": "\uac00\ub8e8/\ubd84\ub9d0\ub958", "category3": "\uae30\ud0c0\ubd84\ub9d0\uac00\ub8e8", "category4": ""}, {"title": "\uac00\ub9bc <b>\ud669\uce58\uc988</b>\ub9db <b>\ubd84\ub9d0 1kg</b> \uce58\uc988\uac00\ub8e8 \ubca0\uc774\ud0b9\uac00\ub8e8 \ud648\ubca0\uc774\ud0b9", "link": "https://search.shopping.naver.com/gate.nhn?id=83095570642", "image": "https://shopping-phinf.pstatic.net/main_8309557/83095570642.jpg", "lprice": "12000", "hprice": "", "mallName": "\uba39\ub530", "productId": "83095570642", "productType": "2", "brand": "\uac00\ub9bc", "maker": "\uac00\ub9bc", "category1": "\uc2dd\ud488", "category2": "\uac00\ub8e8/\ubd84\ub9d0\ub958", "category3": "\uae30\ud0c0\ubd84\ub9d0\uac00\ub8e8", "category4": ""}, {"title": "0178. <b>\ud669\uce58\uc988\ubd84\ub9d0</b> - \uac00\ub9bc<b>1kg</b>", "link": "https://search.shopping.naver.com/gate.nhn?id=81954877350", "image": "https://shopping-phinf.pstatic.net/main_8195487/81954877350.1.jpg", "lprice": "11900", "hprice": "", "mallName": "\ubca0\uc774\ud0b9\ub3c4\uc804", "productId": "81954877350", "productType": "2", "brand": "", "maker": "", "category1": "\uc2dd\ud488", "category2": "\uac00\ub8e8/\ubd84\ub9d0\ub958", "category3": "\uae30\ud0c0\ubd84\ub9d0\uac00\ub8e8", "category4": ""}, {"title": "\uc11c\uac15 <b>\ud669\uce58\uc988\ubd84\ub9d0</b>\uac00\ub8e8 <b>1kg</b>", "link": "https://search.shopping.naver.com/gate.nhn?id=28743105419", "image": "https://shopping-phinf.pstatic.net/main_2874310/28743105419.1.jpg", "lprice": "11300", "hprice": "", "mallName": "\ubca0\uc774\ud0b9\ub9d8", "productId": "28743105419", "productType": "2", "brand": "", "maker": "\uc11c\uac15\uc720\uc5c5", "category1": "\uc2dd\ud488", "category2": "\uac00\ub8e8/\ubd84\ub9d0\ub958", "category3": "\uae30\ud0c0\ubd84\ub9d0\uac00\ub8e8", "category4": ""}, {"title": "<b>\ud669\uce58\uc988 \ubd84\ub9d0</b> \uac00\ub8e8 <b>1kg</b> \ucf00\uc774\ud06c \ucfe0\ud0a4 \ud06c\ub7fc\ube14 \ube75", "link": "https://search.shopping.naver.com/gate.nhn?id=12909610677", "image": "https://shopping-phinf.pstatic.net/main_1290961/12909610677.5.jpg", "lprice": "13700", "hprice": "", "mallName": "\ubca0\uc774\ud0b9\uc870\uc774", "productId": "12909610677", "productType": "2", "brand": "", "maker": "\uaf2c\ubbf8\ub2e4", "category1": "\uc2dd\ud488", "category2": "\uac00\ub8e8/\ubd84\ub9d0\ub958", "category3": "\uae30\ud0c0\ubd84\ub9d0\uac00\ub8e8", "category4": ""}, {"title": "\uaf2c\ubbf8\ub2e4 <b>\ud669\uce58\uc988</b> \ud63c\ud569<b>\ubd84\ub9d0 1kg</b>/ <b>\ud669\uce58\uc988</b>\uac00\ub8e8,\ud30c\uc6b0\ub354,\ud30c\uc6b0\ub2e4,<b>\ud669\uce58\uc988\ubd84\ub9d0</b>", "link": "https://search.shopping.naver.com/gate.nhn?id=19138388445", "image": "https://shopping-phinf.pstatic.net/main_1913838/19138388445.1.jpg", "lprice": "15400", "hprice": "", "mallName": "\ubca0\uc774\ud0b9\ubaac", "productId": "19138388445", "productType": "2", "brand": "", "maker": "", "category1": "\uc2dd\ud488", "category2": "\uac00\ub8e8/\ubd84\ub9d0\ub958", "category3": "\uae30\ud0c0\ubd84\ub9d0\uac00\ub8e8", "category4": ""}, {"title": "\uce58\uc988\ud63c\ud569<b>\ubd84\ub9d0 1kg</b> <b>\ud669\uce58\uc988</b> \uac00\ub8e8 \uc11c\uac15\uc720\uc5c5 \uc790\uc5f0\uce58\uc988 22.5% \ud568\uc720", "link": "https://search.shopping.naver.com/gate.nhn?id=84972243747", "image": "https://shopping-phinf.pstatic.net/main_8497224/84972243747.jpg", "lprice": "11300", "hprice": "", "mallName": "\ucc29\ud55c\ubca0\uc774\ud0b9", "productId": "84972243747", "productType": "2", "brand": "", "maker": "", "category1": "\uc2dd\ud488", "category2": "\uac00\ub8e8/\ubd84\ub9d0\ub958", "category3": "\uae30\ud0c0\ubd84\ub9d0\uac00\ub8e8", "category4": ""}, {"title": "\uaf2c\ubbf8\ub2e4 <b>\ud669\uce58\uc988\ubd84\ub9d0 1kg</b>/\uac00\ub8e8", "link": "https://search.shopping.naver.com/gate.nhn?id=82074815720", "image": "https://shopping-phinf.pstatic.net/main_8207481/82074815720.jpg", "lprice": "13000", "hprice": "", "mallName": "\ub9d8\ucfe0\ud0b9", "productId": "82074815720", "productType": "2", "brand": "", "maker": "\uaf2c\ubbf8\ub2e4", "category1": "\uc2dd\ud488", "category2": "\uac00\ub8e8/\ubd84\ub9d0\ub958", "category3": "\uae30\ud0c0\ubd84\ub9d0\uac00\ub8e8", "category4": ""}, {"title": "\ub354\ubca0\uc774\ud0b9 <b>\ud669\uce58\uc988\ubd84\ub9d01kg</b>", "link": "https://search.shopping.naver.com/gate.nhn?id=82062271436", "image": "https://shopping-phinf.pstatic.net/main_8206227/82062271436.jpg", "lprice": "17500", "hprice": "", "mallName": "\ub354\ubca0\uc774\ud0b9", "productId": "82062271436", "productType": "2", "brand": "", "maker": "\uc774\ub4e0\ud0c0\uc6b4", "category1": "\uc2dd\ud488", "category2": "\uac00\ub8e8/\ubd84\ub9d0\ub958", "category3": "\uae30\ud0c0\ubd84\ub9d0\uac00\ub8e8", "category4": ""}, {"title": "<b>\ud669\uce58\uc988</b>\ub9db<b>\ubd84\ub9d0 1kg</b> (\uac00\ub9bc)", "link": "https://search.shopping.naver.com/gate.nhn?id=84213012688", "image": "https://shopping-phinf.pstatic.net/main_8421301/84213012688.1.jpg", "lprice": "13600", "hprice": "", "mallName": "\uc9c4\ubcf4\ub78c\ubab0", "productId": "84213012688", "productType": "2", "brand": "", "maker": "\uac00\ub9bc\uc0b0\uc5c5", "category1": "\uc2dd\ud488", "category2": "\uac00\ub8e8/\ubd84\ub9d0\ub958", "category3": "\uae30\ud0c0\ubd84\ub9d0\uac00\ub8e8", "category4": ""}, {"title": "\uaf2c\ubbf8\ub2e4 <b>\ud669\uce58\uc988 \ubd84\ub9d0 1kg</b> \uce58\uc988 \uac00\ub8e8 \ubca0\uc774\ud0b9 \uc7ac\ub8cc", "link": "https://search.shopping.naver.com/gate.nhn?id=85774861726", "image": "https://shopping-phinf.pstatic.net/main_8577486/85774861726.jpg", "lprice": "15300", "hprice": "", "mallName": "\ubca0\uc774\ud0b9\ud31c", "productId": "85774861726", "productType": "2", "brand": "", "maker": "", "category1": "\uc2dd\ud488", "category2": "\uac00\ub8e8/\ubd84\ub9d0\ub958", "category3": "\uae30\ud0c0\ubd84\ub9d0\uac00\ub8e8", "category4": ""}, {"title": "\uaf2c\ubbf8\ub2e4 <b>\ud669\uce58\uc988\ubd84\ub9d0 1kg</b>", "link": "https://search.shopping.naver.com/gate.nhn?id=84436178197", "image": "https://shopping-phinf.pstatic.net/main_8443617/84436178197.jpg", "lprice": "13800", "hprice": "", "mallName": "\uce74\uc6b0\uc2dd\ud488\ubca0\uc774\ud0b9", "productId": "84436178197", "productType": "2", "brand": "", "maker": "", "category1": "\uc2dd\ud488", "category2": "\uac00\ub8e8/\ubd84\ub9d0\ub958", "category3": "\uae30\ud0c0\ubd84\ub9d0\uac00\ub8e8", "category4": ""}, {"title": "<b>\ud669\uce58\uc988</b>\uac00\ub8e8<b>1kg</b> \uce58\uc988\ud63c\ud569<b>\ubd84\ub9d0</b> \uc11c\uac15\uc720\uc5c5", "link": "https://search.shopping.naver.com/gate.nhn?id=82453327645", "image": "https://shopping-phinf.pstatic.net/main_8245332/82453327645.jpg", "lprice": "13300", "hprice": "", "mallName": "\ubca0\uc774\ud0b9\uc2a4\ud0c0", "productId": "82453327645", "productType": "2", "brand": "", "maker": "\uc11c\uac15\uc720\uc5c5", "category1": "\uc2dd\ud488", "category2": "\uac00\ub8e8/\ubd84\ub9d0\ub958", "category3": "\uae30\ud0c0\ubd84\ub9d0\uac00\ub8e8", "category4": ""}, {"title": "\uac00\ub9bc <b>\ud669\uce58\uc988</b>\ub9db<b>\ubd84\ub9d0 1kg</b> /<b>\ud669\uce58\uc988</b>\uac00\ub8e8,<b>\ud669\uce58\uc988\ubd84\ub9d0</b>", "link": "https://search.shopping.naver.com/gate.nhn?id=35646371494", "image": "https://shopping-phinf.pstatic.net/main_3564637/35646371494.jpg", "lprice": "13000", "hprice": "", "mallName": "\ubca0\uc774\ud0b9\ubaac", "productId": "35646371494", "productType": "2", "brand": "", "maker": "", "category1": "\uc2dd\ud488", "category2": "\uac00\ub8e8/\ubd84\ub9d0\ub958", "category3": "\uae30\ud0c0\ubd84\ub9d0\uac00\ub8e8", "category4": ""}, {"title": "<b>\ud669\uce58\uc988</b>\uac00\ub8e8 <b>1kg</b>, <b>\ud669\uce58\uc988\ubd84\ub9d0</b>", "link": "https://search.shopping.naver.com/gate.nhn?id=82146104897", "image": "https://shopping-phinf.pstatic.net/main_8214610/82146104897.jpg", "lprice": "19600", "hprice": "", "mallName": "\ud5ec\ub85c\uc6b0\ucf54\uc2a4\ud2b8", "productId": "82146104897", "productType": "2", "brand": "", "maker": "", "category1": "\uc2dd\ud488", "category2": "\uac00\ub8e8/\ubd84\ub9d0\ub958", "category3": "\uae30\ud0c0\ubd84\ub9d0\uac00\ub8e8", "category4": ""}, {"title": "\uc11c\uac15 \uce58\uc988\ud63c\ud569<b>\ubd84\ub9d0 1kg</b> \uc11c\uac15 <b>\ud669\uce58\uc988</b>\uac00\ub8e8", "link": "https://search.shopping.naver.com/gate.nhn?id=84782060253", "image": "https://shopping-phinf.pstatic.net/main_8478206/84782060253.jpg", "lprice": "11890", "hprice": "", "mallName": "\ud310\ub2e4\uc0c1\uc810", "productId": "84782060253", "productType": "2", "brand": "", "maker": "", "category1": "\uc2dd\ud488", "category2": "\uac00\ub8e8/\ubd84\ub9d0\ub958", "category3": "\uae30\ud0c0\ubd84\ub9d0\uac00\ub8e8", "category4": ""}, {"title": "\uaf2c\ubbf8\ub2e4 <b>\ud669\uce58\uc988</b>\uac00\ub8e8 <b>1kg</b> <b>\ud669\uce58\uc988\ubd84\ub9d0</b> \ucfe0\ud0a4 \uba38\ud540 \ud30c\uc6b4\ub4dc\ucf00\uc774\ud06c \ubca0\uc774\ud0b9\uc7ac\ub8cc", "link": "https://search.shopping.naver.com/gate.nhn?id=81464933053", "image": "https://shopping-phinf.pstatic.net/main_8146493/81464933053.1.jpg", "lprice": "13900", "hprice": "", "mallName": "\ud558\ub098 \ubca0\uc774\ud0b9\ud478\ub4dc", "productId": "81464933053", "productType": "2", "brand": "\uc11c\uac15", "maker": "", "category1": "\uc2dd\ud488", "category2": "\uac00\ub8e8/\ubd84\ub9d0\ub958", "category3": "\uae30\ud0c0\ubd84\ub9d0\uac00\ub8e8", "category4": ""}, {"title": "\uc720\ub2c8\ud06c <b>\ud669\uce58\uc988 \ubd84\ub9d0 1kg</b>", "link": "https://search.shopping.naver.com/gate.nhn?id=35173808689", "image": "https://shopping-phinf.pstatic.net/main_3517380/35173808689.1.jpg", "lprice": "11500", "hprice": "", "mallName": "\ucfe0\ud321", "productId": "35173808689", "productType": "2", "brand": "\uc720\ub2c8\ub044", "maker": "", "category1": "\uc2dd\ud488", "category2": "\uac00\ub8e8/\ubd84\ub9d0\ub958", "category3": "\uae30\ud0c0\ubd84\ub9d0\uac00\ub8e8", "category4": ""}, {"title": "\uaf2c\ubbf8\ub2e4 <b>\ud669\uce58\uc988\ubd84\ub9d0 1kg</b> \uce58\uc988 \ud63c\ud569\ubd84\ub9d0 \ud669\uce58\uc988\uac00\ub8e8", "link": "https://search.shopping.naver.com/gate.nhn?id=37800652448", "image": "https://shopping-phinf.pstatic.net/main_3780065/37800652448.jpg", "lprice": "13000", "hprice": "", "mallName": "\uc0ac\ub974\ub974\ucfe1", "productId": "37800652448", "productType": "2", "brand": "", "maker": "", "category1": "\uc2dd\ud488", "category2": "\uac00\ub8e8/\ubd84\ub9d0\ub958", "category3": "\uae30\ud0c0\ubd84\ub9d0\uac00\ub8e8", "category4": ""}, {"title": "\uaf2c\ubbf8\ub2e4 <b>\ud669\uce58\uc988\ubd84\ub9d0 1kg</b> \uce58\uc988 \ud63c\ud569\ubd84\ub9d0 \ud669\uce58\uc988\uac00\ub8e8", "link": "https://search.shopping.naver.com/gate.nhn?id=37800615414", "image": "https://shopping-phinf.pstatic.net/main_3780061/37800615414.jpg", "lprice": "13000", "hprice": "", "mallName": "\ubca0\uc774\ud0b9\ud1a1", "productId": "37800615414", "productType": "2", "brand": "", "maker": "", "category1": "\uc2dd\ud488", "category2": "\uac00\ub8e8/\ubd84\ub9d0\ub958", "category3": "\uae30\ud0c0\ubd84\ub9d0\uac00\ub8e8", "category4": ""}, {"title": "\uac00\ub9bc <b>\ud669\uce58\uc988</b>\ub9db <b>\ubd84\ub9d0 1kg</b> \uce58\uc988\uac00\ub8e8 \ubca0\uc774\ud0b9\uac00\ub8e8 \ud648\ubca0\uc774\ud0b9", "link": "https://search.shopping.naver.com/gate.nhn?id=83860075422", "image": "https://shopping-phinf.pstatic.net/main_8386007/83860075422.1.jpg", "lprice": "13200", "hprice": "", "mallName": "\uc5e3\ud648045", "productId": "83860075422", "productType": "2", "brand": "\uc5e3\ud648045", "maker": "\uac00\ub78c\uc778\ud130\ub124\uc154\ub110", "category1": "\uc2dd\ud488", "category2": "\uac00\ub8e8/\ubd84\ub9d0\ub958", "category3": "\uae30\ud0c0\ubd84\ub9d0\uac00\ub8e8", "category4": ""}, {"title": "\uc11c\uac15 <b>\ud669\uce58\uc988\ubd84\ub9d0 1kg</b>", "link": "https://search.shopping.naver.com/gate.nhn?id=34490706675", "image": "https://shopping-phinf.pstatic.net/main_3449070/34490706675.jpg", "lprice": "12380", "hprice": "", "mallName": "G\ub9c8\ucf13", "productId": "34490706675", "productType": "2", "brand": "", "maker": "", "category1": "\uc2dd\ud488", "category2": "\uac00\ub8e8/\ubd84\ub9d0\ub958", "category3": "\uae30\ud0c0\ubd84\ub9d0\uac00\ub8e8", "category4": ""}, {"title": "<b>\ud669\uce58\uc988</b>\ub9db<b>\ubd84\ub9d0</b> 100g/<b>1kg</b>", "link": "https://search.shopping.naver.com/gate.nhn?id=9581053739", "image": "https://shopping-phinf.pstatic.net/main_9581053/9581053739.jpg", "lprice": "1700", "hprice": "", "mallName": "\ube44\ud55c\uc2a4", "productId": "9581053739", "productType": "2", "brand": "", "maker": "", "category1": "\uc2dd\ud488", "category2": "\uac00\ub8e8/\ubd84\ub9d0\ub958", "category3": "\uae30\ud0c0\ubd84\ub9d0\uac00\ub8e8", "category4": ""}, {"title": "<b>\ud669\uce58\uc988 \ubd84\ub9d0 1kg</b> \uc11c\uac15 / \ud669\uc0c9 \uce58\uc988\ud63c\ud569\ubd84\ub9d0 \uc81c\ube75\uc6a9 \ub9c8\uce74\ub871 \ud1a0\ud551 / \ud648\ubca0\uc774\ud0b9", "link": "https://search.shopping.naver.com/gate.nhn?id=82415470432", "image": "https://shopping-phinf.pstatic.net/main_8241547/82415470432.jpg", "lprice": "13000", "hprice": "", "mallName": "\ud558\uc774\ube0c\ub808\ub4dc", "productId": "82415470432", "productType": "2", "brand": "", "maker": "\uc11c\uac15\uc720\uc5c5", "category1": "\uc2dd\ud488", "category2": "\uac00\ub8e8/\ubd84\ub9d0\ub958", "category3": "\uae30\ud0c0\ubd84\ub9d0\uac00\ub8e8", "category4": ""}, {"title": "<b>\ud669\uce58\uc988</b>\ub9db <b>\ubd84\ub9d0 1kg</b> <b>\ud669\uce58\uc988</b>\uac00\ub8e8 \ubca0\uc774\ud0b9\uc7ac\ub8cc \uac00\ub9bc", "link": "https://search.shopping.naver.com/gate.nhn?id=85673941815", "image": "https://shopping-phinf.pstatic.net/main_8567394/85673941815.jpg", "lprice": "13900", "hprice": "", "mallName": "\ud558\ub098 \ubca0\uc774\ud0b9\ud478\ub4dc", "productId": "85673941815", "productType": "2", "brand": "\uac00\ub9bc", "maker": "", "category1": "\uc2dd\ud488", "category2": "\uac00\ub8e8/\ubd84\ub9d0\ub958", "category3": "\uae30\ud0c0\ubd84\ub9d0\uac00\ub8e8", "category4": ""}, {"title": "<b>\ud669\uce58\uc988</b>\ub9db<b>\ubd84\ub9d0</b> (200g,<b>1kg</b>)", "link": "https://search.shopping.naver.com/gate.nhn?id=22208469435", "image": "https://shopping-phinf.pstatic.net/main_2220846/22208469435.jpg", "lprice": "2990", "hprice": "", "mallName": "\uc6f0\ubca0\uc774\ud0b9", "productId": "22208469435", "productType": "2", "brand": "", "maker": "", "category1": "\uc2dd\ud488", "category2": "\uac00\ub8e8/\ubd84\ub9d0\ub958", "category3": "\uae30\ud0c0\ubd84\ub9d0\uac00\ub8e8", "category4": ""}, {"title": "\uac00\ub9bc <b>\ud669\uce58\uc988</b>\ub9db <b>\ubd84\ub9d0 1kg</b> <b>\ud669\uce58\uc988</b>\uac00\ub8e8 \ubca0\uc774\ud0b9\uc7ac\ub8cc \ud648\ubca0\uc774\ud0b9", "link": "https://search.shopping.naver.com/gate.nhn?id=85678798182", "image": "https://shopping-phinf.pstatic.net/main_8567879/85678798182.1.jpg", "lprice": "13900", "hprice": "", "mallName": "\uc774\uc9c0 \ubca0\uc774\ud0b9", "productId": "85678798182", "productType": "2", "brand": "", "maker": "", "category1": "\uc2dd\ud488", "category2": "\uac00\ub8e8/\ubd84\ub9d0\ub958", "category3": "\uae30\ud0c0\ubd84\ub9d0\uac00\ub8e8", "category4": ""}, {"title": "\uac00\ub9bc <b>\ud669\uce58\uc988</b>\ub9db<b>\ubd84\ub9d0 1KG</b> <b>\ud669\uce58\uc988</b>\uac00\ub8e8", "link": "https://search.shopping.naver.com/gate.nhn?id=85775332162", "image": "https://shopping-phinf.pstatic.net/main_8577533/85775332162.jpg", "lprice": "13700", "hprice": "", "mallName": "\uad6d\ub300\ubca0\uc774\ud0b9", "productId": "85775332162", "productType": "2", "brand": "\uac00\ub9bc", "maker": "", "category1": "\uc2dd\ud488", "category2": "\uac00\ub8e8/\ubd84\ub9d0\ub958", "category3": "\uae30\ud0c0\ubd84\ub9d0\uac00\ub8e8", "category4": ""}, {"title": "\uc774\ub4e0 <b>\ud669\uce58\uc988 \ubd84\ub9d01kg</b>(\uc774\ub4e0\ud0c0\uc6b4)", "link": "https://search.shopping.naver.com/gate.nhn?id=85106871369", "image": "https://shopping-phinf.pstatic.net/main_8510687/85106871369.jpg", "lprice": "16600", "hprice": "", "mallName": "\ubca0\uc774\ud0b9\ud2b8\ub9ac\ub124\uc624", "productId": "85106871369", "productType": "2", "brand": "", "maker": "", "category1": "\uc2dd\ud488", "category2": "\uac00\ub8e8/\ubd84\ub9d0\ub958", "category3": "\uae30\ud0c0\ubd84\ub9d0\uac00\ub8e8", "category4": ""}, {"title": "\uc774\ub4e0 <b>\ud669\uce58\uc988\ubd84\ub9d0 1kg</b> \uc774\ub4e0\ud0c0\uc6b4 \ud669\uce58\uc988\uac00\ub8e8", "link": "https://search.shopping.naver.com/gate.nhn?id=85394938756", "image": "https://shopping-phinf.pstatic.net/main_8539493/85394938756.jpg", "lprice": "16300", "hprice": "", "mallName": "\ud478\ub514\uc26c", "productId": "85394938756", "productType": "2", "brand": "\uc774\ub4e0", "maker": "\uc11c\uac15\uc720\uc5c5", "category1": "\uc2dd\ud488", "category2": "\uac00\ub8e8/\ubd84\ub9d0\ub958", "category3": "\uae30\ud0c0\ubd84\ub9d0\uac00\ub8e8", "category4": ""}, {"title": "<b>\ud669\uce58\uc988\ubd84\ub9d0 1kg</b>/\uaf2c\ubbf8\ub2e4 \ud669\uce58\uc988", "link": "https://search.shopping.naver.com/gate.nhn?id=8664837755", "image": "https://shopping-phinf.pstatic.net/main_8664837/8664837755.jpg", "lprice": "13880", "hprice": "", "mallName": "\uce74\uc6b0\uc2dd\ud488", "productId": "8664837755", "productType": "2", "brand": "", "maker": "\uaf2c\ubbf8\ub2e4", "category1": "\uc2dd\ud488", "category2": "\uac00\ub8e8/\ubd84\ub9d0\ub958", "category3": "\uae30\ud0c0\ubd84\ub9d0\uac00\ub8e8", "category4": ""}, {"title": "<b>\ud669\uce58\uc988\ubd84\ub9d0 1kg</b>", "link": "https://search.shopping.naver.com/gate.nhn?id=21833036986", "image": "https://shopping-phinf.pstatic.net/main_2183303/21833036986.jpg", "lprice": "17800", "hprice": "", "mallName": "\ucfe0\ud0a4\ubca0\ubca0", "productId": "21833036986", "productType": "2", "brand": "\uc774\ub4e0", "maker": "", "category1": "\uc2dd\ud488", "category2": "\uac00\ub8e8/\ubd84\ub9d0\ub958", "category3": "\uae30\ud0c0\ubd84\ub9d0\uac00\ub8e8", "category4": ""}, {"title": "<b>\ud669\uce58\uc988</b>\ub9db<b>\ubd84\ub9d0 1kg</b>", "link": "https://search.shopping.naver.com/gate.nhn?id=84578816084", "image": "https://shopping-phinf.pstatic.net/main_8457881/84578816084.jpg", "lprice": "11700", "hprice": "", "mallName": "\ube44\ud55c\uc2a4", "productId": "84578816084", "productType": "2", "brand": "", "maker": "", "category1": "\uc2dd\ud488", "category2": "\uac00\ub8e8/\ubd84\ub9d0\ub958", "category3": "\uae30\ud0c0\ubd84\ub9d0\uac00\ub8e8", "category4": ""}, {"title": "<b>\ud669\uce58\uc988 \ubd84\ub9d0</b> \uac00\ub9bc <b>1Kg</b> \uac00\ub8e8 \uc2dd\uc790\uc7ac \uc804\ubb38\uc810 \uc5c5\uc18c\uc6a9", "link": "https://search.shopping.naver.com/gate.nhn?id=38644396515", "image": "https://shopping-phinf.pstatic.net/main_3864439/38644396515.jpg", "lprice": "48540", "hprice": "", "mallName": "\uc2e0\uc0c1", "productId": "38644396515", "productType": "2", "brand": "", "maker": "", "category1": "\uc2dd\ud488", "category2": "\uac00\ub8e8/\ubd84\ub9d0\ub958", "category3": "\uae30\ud0c0\ubd84\ub9d0\uac00\ub8e8", "category4": ""}, {"title": "[\uc11c\uac15\uc720\uc5c5] <b>\ud669\uce58\uc988\ubd84\ub9d01kg</b> [\uce58\uc988\ud63c\ud569\ubd84\ub9d0]", "link": "https://search.shopping.naver.com/gate.nhn?id=85827855490", "image": "https://shopping-phinf.pstatic.net/main_8582785/85827855490.jpg", "lprice": "12500", "hprice": "", "mallName": "\uc544\ub9c8\uc874\ubca0\uc774\ud0b9", "productId": "85827855490", "productType": "2", "brand": "", "maker": "", "category1": "\uc2dd\ud488", "category2": "\uac00\ub8e8/\ubd84\ub9d0\ub958", "category3": "\uae30\ud0c0\ubd84\ub9d0\uac00\ub8e8", "category4": ""}, {"title": "\ubca0\uc774\ud0b9\uc58c \uc774\ub4e0\ud0c0\uc6b4 <b>\ud669\uce58\uc988\ubd84\ub9d0 1kg</b>", "link": "https://search.shopping.naver.com/gate.nhn?id=29141430073", "image": "https://shopping-phinf.pstatic.net/main_2914143/29141430073.jpg", "lprice": "17450", "hprice": "", "mallName": "\ucfe0\ud321", "productId": "29141430073", "productType": "2", "brand": "\uc774\ub4e0\ud0c0\uc6b4", "maker": "", "category1": "\uc2dd\ud488", "category2": "\uac00\ub8e8/\ubd84\ub9d0\ub958", "category3": "\uae30\ud0c0\ubd84\ub9d0\uac00\ub8e8", "category4": ""}, {"title": "<b>\ud669\uce58\uc988\ubd84\ub9d0 1kg</b> \ud669\uce58\uc988 \uac00\ub8e8 \ud63c\ud569\uce58\uc988", "link": "https://search.shopping.naver.com/gate.nhn?id=80859424571", "image": "https://shopping-phinf.pstatic.net/main_8085942/80859424571.jpg", "lprice": "16000", "hprice": "", "mallName": "\uc194\uadf8\ub9b0", "productId": "80859424571", "productType": "2", "brand": "", "maker": "", "category1": "\uc2dd\ud488", "category2": "\uac00\ub8e8/\ubd84\ub9d0\ub958", "category3": "\uae30\ud0c0\ubd84\ub9d0\uac00\ub8e8", "category4": ""}, {"title": "\uc11c\uac15 <b>\ud669\uce58\uc988\ubd84\ub9d0 1kg</b>", "link": "https://search.shopping.naver.com/gate.nhn?id=38635597631", "image": "https://shopping-phinf.pstatic.net/main_3863559/38635597631.jpg", "lprice": "21330", "hprice": "", "mallName": "\uc625\uc158", "productId": "38635597631", "productType": "2", "brand": "", "maker": "", "category1": "\uc2dd\ud488", "category2": "\uac00\ub8e8/\ubd84\ub9d0\ub958", "category3": "\uae30\ud0c0\ubd84\ub9d0\uac00\ub8e8", "category4": ""}, {"title": "\uc5c5\uc18c\uc6a9 \uc2dd\ub2f9 \uc2dd\uc790\uc7ac \uc8fc\ubc29 \uc7ac\ub8cc <b>\ud669\uce58\uc988\ubd84\ub9d0 1kg</b> X5", "link": "https://search.shopping.naver.com/gate.nhn?id=38613938132", "image": "https://shopping-phinf.pstatic.net/main_3861393/38613938132.jpg", "lprice": "101970", "hprice": "", "mallName": "\uc774\uc7a5\uc0ac\ub9ac\ube59", "productId": "38613938132", "productType": "2", "brand": "", "maker": "\uac00\ub9bc\uc0b0\uc5c5", "category1": "\uc2dd\ud488", "category2": "\uac00\ub8e8/\ubd84\ub9d0\ub958", "category3": "\uae30\ud0c0\ubd84\ub9d0\uac00\ub8e8", "category4": ""}, {"title": "\ud669\uce58\uc988\uac00\ub8e8 <b>\ud669\uce58\uc988 \ubd84\ub9d0 1kg</b>", "link": "https://search.shopping.naver.com/gate.nhn?id=84705413543", "image": "https://shopping-phinf.pstatic.net/main_8470541/84705413543.jpg", "lprice": "22900", "hprice": "", "mallName": "\uc218\uc815\uc885\ud569\ud310\ub9e4", "productId": "84705413543", "productType": "2", "brand": "", "maker": "\uc11c\uac15\uc720\uc5c5", "category1": "\uc2dd\ud488", "category2": "\uac00\ub8e8/\ubd84\ub9d0\ub958", "category3": "\uae30\ud0c0\ubd84\ub9d0\uac00\ub8e8", "category4": ""}, {"title": "\uac00\ub9bc \uc9c4\ud55c <b>\ud669\uce58\uc988</b> \ub9db \uac00\ub8e8 <b>\ubd84\ub9d0 1kg</b>", "link": "https://search.shopping.naver.com/gate.nhn?id=82294963954", "image": "https://shopping-phinf.pstatic.net/main_8229496/82294963954.jpg", "lprice": "13200", "hprice": "", "mallName": "\ubca0\uc774\ud0b9\ub9d8", "productId": "82294963954", "productType": "2", "brand": "", "maker": "", "category1": "\uc2dd\ud488", "category2": "\uac00\ub8e8/\ubd84\ub9d0\ub958", "category3": "\uae30\ud0c0\ubd84\ub9d0\uac00\ub8e8", "category4": ""}, {"title": "\uc11c\uac15 <b>\ud669\uce58\uc988\ubd84\ub9d0  1kg</b>  3\uac1c", "link": "https://search.shopping.naver.com/gate.nhn?id=31276788550", "image": "https://shopping-phinf.pstatic.net/main_3127678/31276788550.20.jpg", "lprice": "37050", "hprice": "", "mallName": "\ucfe0\ud321", "productId": "31276788550", "productType": "2", "brand": "\uc11c\uac15", "maker": "\uc11c\uac15", "category1": "\uc2dd\ud488", "category2": "\uac00\ub8e8/\ubd84\ub9d0\ub958", "category3": "\uae30\ud0c0\ubd84\ub9d0\uac00\ub8e8", "category4": ""}, {"title": "\uc11c\uac15 <b>\ud669\uce58\uc988 \ubd84\ub9d01kg</b>", "link": "https://search.shopping.naver.com/gate.nhn?id=85106871528", "image": "https://shopping-phinf.pstatic.net/main_8510687/85106871528.jpg", "lprice": "13600", "hprice": "", "mallName": "\ubca0\uc774\ud0b9\ud2b8\ub9ac\ub124\uc624", "productId": "85106871528", "productType": "2", "brand": "", "maker": "", "category1": "\uc2dd\ud488", "category2": "\uac00\ub8e8/\ubd84\ub9d0\ub958", "category3": "\uae30\ud0c0\ubd84\ub9d0\uac00\ub8e8", "category4": ""}, {"title": "<b>\ud669\uce58\uc988\ubd84\ub9d01kg</b>", "link": "https://search.shopping.naver.com/gate.nhn?id=35114178290", "image": "https://shopping-phinf.pstatic.net/main_3511417/35114178290.jpg", "lprice": "11600", "hprice": "", "mallName": "\ubca0\uc774\ud0b9\uc58c", "productId": "35114178290", "productType": "2", "brand": "", "maker": "", "category1": "\uc2dd\ud488", "category2": "\uac00\ub8e8/\ubd84\ub9d0\ub958", "category3": "\uae30\ud0c0\ubd84\ub9d0\uac00\ub8e8", "category4": ""}, {"title": "\uc774\ub4e0\ud0c0\uc6b4 <b>\ud669\uce58\uc988\ubd84\ub9d0 1kg</b>", "link": "https://search.shopping.naver.com/gate.nhn?id=29130400658", "image": "https://shopping-phinf.pstatic.net/main_2913040/29130400658.jpg", "lprice": "16300", "hprice": "", "mallName": "\ubca0\uc774\ud0b9\uc58c", "productId": "29130400658", "productType": "2", "brand": "", "maker": "", "category1": "\uc2dd\ud488", "category2": "\uac00\ub8e8/\ubd84\ub9d0\ub958", "category3": "\uae30\ud0c0\ubd84\ub9d0\uac00\ub8e8", "category4": ""}, {"title": "\uac00\ub9bc <b>\ud669\uce58\uc988 \ubd84\ub9d01kg</b>", "link": "https://search.shopping.naver.com/gate.nhn?id=33006678807", "image": "https://shopping-phinf.pstatic.net/main_3300667/33006678807.jpg", "lprice": "12300", "hprice": "", "mallName": "palscloset", "productId": "33006678807", "productType": "2", "brand": "", "maker": "", "category1": "\uc2dd\ud488", "category2": "\uac00\ub8e8/\ubd84\ub9d0\ub958", "category3": "\uae30\ud0c0\ubd84\ub9d0\uac00\ub8e8", "category4": ""}, {"title": "\uc774\ub4e0 <b>\ud669\uce58\uc988 \ubd84\ub9d01kg</b>(\uc774\ub4e0\ud0c0\uc6b4)", "link": "https://search.shopping.naver.com/gate.nhn?id=29342580756", "image": "https://shopping-phinf.pstatic.net/main_2934258/29342580756.19.jpg", "lprice": "18600", "hprice": "", "mallName": "\ucfe0\ud321", "productId": "29342580756", "productType": "2", "brand": "", "maker": "", "category1": "\uc2dd\ud488", "category2": "\uac00\ub8e8/\ubd84\ub9d0\ub958", "category3": "\uae30\ud0c0\ubd84\ub9d0\uac00\ub8e8", "category4": ""}, {"title": "\uc11c\uac15 <b>\ud669\uce58\uc988 \ubd84\ub9d01kg</b>", "link": "https://search.shopping.naver.com/gate.nhn?id=30730714093", "image": "https://shopping-phinf.pstatic.net/main_3073071/30730714093.jpg", "lprice": "13600", "hprice": "", "mallName": "palscloset", "productId": "30730714093", "productType": "2", "brand": "", "maker": "", "category1": "\uc2dd\ud488", "category2": "\uac00\ub8e8/\ubd84\ub9d0\ub958", "category3": "\uae30\ud0c0\ubd84\ub9d0\uac00\ub8e8", "category4": ""}, {"title": "\uac00\ub9bc <b>\ud669\uce58\uc988\ubd84\ub9d0 1Kg</b>", "link": "https://search.shopping.naver.com/gate.nhn?id=13363864891", "image": "https://shopping-phinf.pstatic.net/main_1336386/13363864891.jpg", "lprice": "13800", "hprice": "", "mallName": "\uc720\uc5b4\ub514\uc2dc", "productId": "13363864891", "productType": "2", "brand": "", "maker": "", "category1": "\uc2dd\ud488", "category2": "\uac00\ub8e8/\ubd84\ub9d0\ub958", "category3": "\uae30\ud0c0\ubd84\ub9d0\uac00\ub8e8", "category4": ""}, {"title": "<b>\ud669\uce58\uc988\ubd84\ub9d0 1kg</b> \ud669\uce58\uc988\uac00\ub8e8 \ud63c\ud569\uce58\uc988 \ud669\uce58\uc988", "link": "https://search.shopping.naver.com/gate.nhn?id=27895664056", "image": "https://shopping-phinf.pstatic.net/main_2789566/27895664056.1.jpg", "lprice": "17200", "hprice": "", "mallName": "\uc625\uc158", "productId": "27895664056", "productType": "2", "brand": "", "maker": "", "category1": "\uc2dd\ud488", "category2": "\uac00\ub8e8/\ubd84\ub9d0\ub958", "category3": "\uae30\ud0c0\ubd84\ub9d0\uac00\ub8e8", "category4": ""}, {"title": "\uc11c\uac15 <b>\ud669\uce58\uc988 \ubd84\ub9d01kg</b>", "link": "https://search.shopping.naver.com/gate.nhn?id=30740012918", "image": "https://shopping-phinf.pstatic.net/main_3074001/30740012918.12.jpg", "lprice": "15100", "hprice": "", "mallName": "\ucfe0\ud321", "productId": "30740012918", "productType": "2", "brand": "", "maker": "", "category1": "\uc2dd\ud488", "category2": "\uac00\ub8e8/\ubd84\ub9d0\ub958", "category3": "\uae30\ud0c0\ubd84\ub9d0\uac00\ub8e8", "category4": ""}, {"title": "\uac00\ub9bc <b>\ud669\uce58\uc988 \ubd84\ub9d01kg</b>", "link": "https://search.shopping.naver.com/gate.nhn?id=29810301591", "image": "https://shopping-phinf.pstatic.net/main_2981030/29810301591.12.jpg", "lprice": "13700", "hprice": "", "mallName": "\ucfe0\ud321", "productId": "29810301591", "productType": "2", "brand": "", "maker": "", "category1": "\uc2dd\ud488", "category2": "\uac00\ub8e8/\ubd84\ub9d0\ub958", "category3": "\uae30\ud0c0\ubd84\ub9d0\uac00\ub8e8", "category4": ""}, {"title": "<b>\ud669\uce58\uc988\ubd84\ub9d0 1kg</b>", "link": "https://search.shopping.naver.com/gate.nhn?id=82790403964", "image": "https://shopping-phinf.pstatic.net/main_8279040/82790403964.jpg", "lprice": "16500", "hprice": "", "mallName": "\ub378\ub9ac\ubd81", "productId": "82790403964", "productType": "2", "brand": "", "maker": "", "category1": "\uc2dd\ud488", "category2": "\uac00\ub8e8/\ubd84\ub9d0\ub958", "category3": "\uae30\ud0c0\ubd84\ub9d0\uac00\ub8e8", "category4": ""}, {"title": "<b>\ud669\uce58\uc988 \ubd84\ub9d0</b> \uac00\ub9bc <b>1Kg</b> X15\uac1c \uac00\ub8e8 \uc2dd\uc790\uc7ac \uc804\ubb38\uc810", "link": "https://search.shopping.naver.com/gate.nhn?id=38644614771", "image": "https://shopping-phinf.pstatic.net/main_3864461/38644614771.jpg", "lprice": "427966", "hprice": "", "mallName": "\uc2e0\uc0c1", "productId": "38644614771", "productType": "2", "brand": "", "maker": "", "category1": "\uc2dd\ud488", "category2": "\uac00\ub8e8/\ubd84\ub9d0\ub958", "category3": "\uae30\ud0c0\ubd84\ub9d0\uac00\ub8e8", "category4": ""}, {"title": "\uc5c5\uc18c\uc6a9 \uc2dd\ub2f9 \uc2dd\uc790\uc7ac \uac00\ub9bc\uc0b0\uc5c5 <b>\ud669\uce58\uc988\ubd84\ub9d0 1kg</b> X15", "link": "https://search.shopping.naver.com/gate.nhn?id=38613645554", "image": "https://shopping-phinf.pstatic.net/main_3861364/38613645554.jpg", "lprice": "302830", "hprice": "", "mallName": "\uc774\uc7a5\uc0ac\ub9ac\ube59", "productId": "38613645554", "productType": "2", "brand": "", "maker": "\uac00\ub9bc\uc0b0\uc5c5", "category1": "\uc2dd\ud488", "category2": "\uac00\ub8e8/\ubd84\ub9d0\ub958", "category3": "\uae30\ud0c0\ubd84\ub9d0\uac00\ub8e8", "category4": ""}, {"title": "[\uce58\uc988\uac00\ub8e8] \uc774\ub4e0\ud0c0\uc6b4 <b>\ud669\uce58\uc988\ubd84\ub9d0 1kg</b> / \ud669\uce58\uc988 \ud669\uce58\uc988\uac00\ub8e8 \ucfe0\ud0b9 \ubca0\uc774\ud0b9", "link": "https://search.shopping.naver.com/gate.nhn?id=85679353488", "image": "https://shopping-phinf.pstatic.net/main_8567935/85679353488.jpg", "lprice": "14900", "hprice": "", "mallName": "\uc5ec\uc720\ub9c8\ucf13", "productId": "85679353488", "productType": "2", "brand": "", "maker": "", "category1": "\uc2dd\ud488", "category2": "\uac00\ub8e8/\ubd84\ub9d0\ub958", "category3": "\uae30\ud0c0\ubd84\ub9d0\uac00\ub8e8", "category4": ""}, {"title": "\uc5c5\uc18c\uc6a9 \uc2dd\ub2f9 \uc2dd\uc790\uc7ac \uc8fc\ubc29 \uc7ac\ub8cc <b>\ud669\uce58\uc988\ubd84\ub9d0 1kg</b> X5  1", "link": "https://search.shopping.naver.com/gate.nhn?id=37012715316", "image": "https://shopping-phinf.pstatic.net/main_3701271/37012715316.jpg", "lprice": "97870", "hprice": "", "mallName": "\ucfe0\ud321", "productId": "37012715316", "productType": "2", "brand": "", "maker": "\uac00\ub9bc\uc0b0\uc5c5", "category1": "\uc2dd\ud488", "category2": "\uac00\ub8e8/\ubd84\ub9d0\ub958", "category3": "\uae30\ud0c0\ubd84\ub9d0\uac00\ub8e8", "category4": ""}, {"title": "<b>\ud669\uce58\uc988</b>\ub9db<b>\ubd84\ub9d0 1kg</b>", "link": "https://search.shopping.naver.com/gate.nhn?id=11415185510", "image": "https://shopping-phinf.pstatic.net/main_1141518/11415185510.jpg", "lprice": "15800", "hprice": "", "mallName": "\ub9d8\uc2a4\uc624\ube10", "productId": "11415185510", "productType": "2", "brand": "", "maker": "\uac00\ub9bc\uc0b0\uc5c5", "category1": "\uc2dd\ud488", "category2": "\uac00\ub8e8/\ubd84\ub9d0\ub958", "category3": "\uae30\ud0c0\ubd84\ub9d0\uac00\ub8e8", "category4": ""}, {"title": "\uc11c\uac15 <b>\ud669\uce58\uc988 \ubd84\ub9d0 1kg</b> / \uce58\uc988\ud63c\ud569\ubd84\ub9d0 \uc9c4\ud55c\ud48d\ubbf8 \uc81c\ube75\uc6a9 \ub9c8\uce74\ub871 \ud1a0\ud551 / \ud648\ubca0\uc774\ud0b9", "link": "https://search.shopping.naver.com/gate.nhn?id=82415470838", "image": "https://shopping-phinf.pstatic.net/main_8241547/82415470838.jpg", "lprice": "13000", "hprice": "", "mallName": "sm\uc720\ud1b5", "productId": "82415470838", "productType": "2", "brand": "", "maker": "\uc11c\uac15\uc720\uc5c5", "category1": "\uc2dd\ud488", "category2": "\uac00\ub8e8/\ubd84\ub9d0\ub958", "category3": "\uae30\ud0c0\ubd84\ub9d0\uac00\ub8e8", "category4": ""}, {"title": "<b>\ud669\uce58\uc988</b>\ub9db<b>\ubd84\ub9d0 1kg</b> / \uac00\ub9bc, <b>\ud669\uce58\uc988</b>\uac00\ub8e8", "link": "https://search.shopping.naver.com/gate.nhn?id=21356956289", "image": "https://shopping-phinf.pstatic.net/main_2135695/21356956289.1.jpg", "lprice": "14200", "hprice": "", "mallName": "\ubca0\uc774\ud0b9\ud310\ub2e4", "productId": "21356956289", "productType": "2", "brand": "", "maker": "", "category1": "\uc2dd\ud488", "category2": "\uac00\ub8e8/\ubd84\ub9d0\ub958", "category3": "\uae30\ud0c0\ubd84\ub9d0\uac00\ub8e8", "category4": ""}, {"title": "\uce58\uc988 \uaf2c\ubbf8\ub2e4 <b>\ud669\uce58\uc988</b> \ud63c\ud569 <b>\ubd84\ub9d0 1kg</b>", "link": "https://search.shopping.naver.com/gate.nhn?id=38798767398", "image": "https://shopping-phinf.pstatic.net/main_3879876/38798767398.jpg", "lprice": "29770", "hprice": "", "mallName": "\uc625\uc158", "productId": "38798767398", "productType": "2", "brand": "", "maker": "", "category1": "\uc2dd\ud488", "category2": "\uac00\ub8e8/\ubd84\ub9d0\ub958", "category3": "\uae30\ud0c0\ubd84\ub9d0\uac00\ub8e8", "category4": ""}, {"title": "<b>\ud669\uce58\uc988 \ubd84\ub9d0</b> \uac00\ub9bc <b>1Kg</b> X5\uac1c \uac00\ub8e8 \uc2dd\uc790\uc7ac \uc804\ubb38\uc810", "link": "https://search.shopping.naver.com/gate.nhn?id=38644221108", "image": "https://shopping-phinf.pstatic.net/main_3864422/38644221108.jpg", "lprice": "156940", "hprice": "", "mallName": "\uc2e0\uc0c1", "productId": "38644221108", "productType": "2", "brand": "", "maker": "", "category1": "\uc2dd\ud488", "category2": "\uac00\ub8e8/\ubd84\ub9d0\ub958", "category3": "\uae30\ud0c0\ubd84\ub9d0\uac00\ub8e8", "category4": ""}, {"title": "[\uac00\ub9bc] <b>\ud669\uce58\uc988</b>\ub9db <b>\ubd84\ub9d0 1kg</b>", "link": "https://search.shopping.naver.com/gate.nhn?id=8205160952", "image": "https://shopping-phinf.pstatic.net/main_8205160/8205160952.jpg", "lprice": "16000", "hprice": "", "mallName": "\uc6b0\uc131\ud648\ubca0\uc774\ud0b9", "productId": "8205160952", "productType": "2", "brand": "", "maker": "", "category1": "\uc2dd\ud488", "category2": "\uac00\ub8e8/\ubd84\ub9d0\ub958", "category3": "\uae30\ud0c0\ubd84\ub9d0\uac00\ub8e8", "category4": ""}, {"title": "\uac00\ub9bc <b>\ud669\uce58\uc988</b>\ub9db <b>\ubd84\ub9d0 1Kg</b> X15\ubd09 \uce58\uc988<b>\ubd84\ub9d0</b> \uce58\uc988\uac00\ub8e8", "link": "https://search.shopping.naver.com/gate.nhn?id=82368044310", "image": "https://shopping-phinf.pstatic.net/main_8236804/82368044310.jpg", "lprice": "266110", "hprice": "", "mallName": "\uc724\uc815\uc774\ub124\ud478\ub4dc", "productId": "82368044310", "productType": "2", "brand": "", "maker": "\uac00\ub9bc\uc0b0\uc5c5", "category1": "\uc2dd\ud488", "category2": "\uac00\ub8e8/\ubd84\ub9d0\ub958", "category3": "\uae30\ud0c0\ubd84\ub9d0\uac00\ub8e8", "category4": ""}, {"title": "\uac00\ub9bc <b>\ud669\uce58\uc988</b>\ub9db <b>\ubd84\ub9d0 1Kg</b> \uce58\uc988<b>\ubd84\ub9d0</b> \uce58\uc988\uac00\ub8e8", "link": "https://search.shopping.naver.com/gate.nhn?id=82368044308", "image": "https://shopping-phinf.pstatic.net/main_8236804/82368044308.jpg", "lprice": "18930", "hprice": "", "mallName": "\uc724\uc815\uc774\ub124\ud478\ub4dc", "productId": "82368044308", "productType": "2", "brand": "", "maker": "\uac00\ub9bc\uc0b0\uc5c5", "category1": "\uc2dd\ud488", "category2": "\uac00\ub8e8/\ubd84\ub9d0\ub958", "category3": "\uae30\ud0c0\ubd84\ub9d0\uac00\ub8e8", "category4": ""}, {"title": "\ud0a4\ubc0d / \uaf2c\ubbf8\ub2e4 <b>\ud669\uce58\uc988</b> \ud63c\ud569 <b>\ubd84\ub9d0 1kg</b>", "link": "https://search.shopping.naver.com/gate.nhn?id=38591628043", "image": "https://shopping-phinf.pstatic.net/main_3859162/38591628043.jpg", "lprice": "35430", "hprice": "", "mallName": "\uc625\uc158", "productId": "38591628043", "productType": "2", "brand": "", "maker": "", "category1": "\uc2dd\ud488", "category2": "\uac00\ub8e8/\ubd84\ub9d0\ub958", "category3": "\uae30\ud0c0\ubd84\ub9d0\uac00\ub8e8", "category4": ""}, {"title": "\ud0a4\ubc0d / \uaf2c\ubbf8\ub2e4 <b>\ud669\uce58\uc988</b> \ud63c\ud569 <b>\ubd84\ub9d0 1kg</b>", "link": "https://search.shopping.naver.com/gate.nhn?id=38588416281", "image": "https://shopping-phinf.pstatic.net/main_3858841/38588416281.jpg", "lprice": "35430", "hprice": "", "mallName": "G\ub9c8\ucf13", "productId": "38588416281", "productType": "2", "brand": "", "maker": "", "category1": "\uc2dd\ud488", "category2": "\uac00\ub8e8/\ubd84\ub9d0\ub958", "category3": "\uae30\ud0c0\ubd84\ub9d0\uac00\ub8e8", "category4": ""}, {"title": "\ud0a4\ubc0d / \uaf2c\ubbf8\ub2e4 <b>\ud669\uce58\uc988</b> \ud63c\ud569 <b>\ubd84\ub9d0 1kg</b>", "link": "https://search.shopping.naver.com/gate.nhn?id=38588232164", "image": "https://shopping-phinf.pstatic.net/main_3858823/38588232164.jpg", "lprice": "32950", "hprice": "", "mallName": "\ub86f\ub370ON", "productId": "38588232164", "productType": "2", "brand": "", "maker": "", "category1": "\uc2dd\ud488", "category2": "\uac00\ub8e8/\ubd84\ub9d0\ub958", "category3": "\uae30\ud0c0\ubd84\ub9d0\uac00\ub8e8", "category4": ""}, {"title": "<b>\ud669\uce58\uc988 \ubd84\ub9d0</b> \uac00\ub9bc <b>1Kg</b> \uac00\ub8e8 \uc2dd\uc790\uc7ac \uc804\ubb38\uc810 \uc5c5\uc18c\uc6a9", "link": "https://search.shopping.naver.com/gate.nhn?id=38521267133", "image": "https://shopping-phinf.pstatic.net/main_3852126/38521267133.jpg", "lprice": "33360", "hprice": "", "mallName": "11\ubc88\uac00", "productId": "38521267133", "productType": "2", "brand": "", "maker": "", "category1": "\uc2dd\ud488", "category2": "\uac00\ub8e8/\ubd84\ub9d0\ub958", "category3": "\uae30\ud0c0\ubd84\ub9d0\uac00\ub8e8", "category4": ""}, {"title": "\uaf2c\ubbf8\ub2e4 <b>\ud669\uce58\uc988</b> \ud63c\ud569 <b>\ubd84\ub9d0 1kg</b>", "link": "https://search.shopping.naver.com/gate.nhn?id=38521186978", "image": "https://shopping-phinf.pstatic.net/main_3852118/38521186978.jpg", "lprice": "29570", "hprice": "", "mallName": "\uc625\uc158", "productId": "38521186978", "productType": "2", "brand": "", "maker": "", "category1": "\uc2dd\ud488", "category2": "\uac00\ub8e8/\ubd84\ub9d0\ub958", "category3": "\uae30\ud0c0\ubd84\ub9d0\uac00\ub8e8", "category4": ""}, {"title": "\uaf2c\ubbf8\ub2e4 <b>\ud669\uce58\uc988</b> \ud63c\ud569 <b>\ubd84\ub9d0 1kg</b>", "link": "https://search.shopping.naver.com/gate.nhn?id=38516802113", "image": "https://shopping-phinf.pstatic.net/main_3851680/38516802113.jpg", "lprice": "29560", "hprice": "", "mallName": "G\ub9c8\ucf13", "productId": "38516802113", "productType": "2", "brand": "", "maker": "", "category1": "\uc2dd\ud488", "category2": "\uac00\ub8e8/\ubd84\ub9d0\ub958", "category3": "\uae30\ud0c0\ubd84\ub9d0\uac00\ub8e8", "category4": ""}, {"title": "\uaf2c\ubbf8\ub2e4 <b>\ud669\uce58\uc988</b> \ud63c\ud569 <b>\ubd84\ub9d0 1kg</b>", "link": "https://search.shopping.naver.com/gate.nhn?id=38503923769", "image": "https://shopping-phinf.pstatic.net/main_3850392/38503923769.jpg", "lprice": "30540", "hprice": "", "mallName": "\uc778\ud130\ud30c\ud06c\uc1fc\ud551", "productId": "38503923769", "productType": "2", "brand": "", "maker": "", "category1": "\uc2dd\ud488", "category2": "\uac00\ub8e8/\ubd84\ub9d0\ub958", "category3": "\uae30\ud0c0\ubd84\ub9d0\uac00\ub8e8", "category4": ""}, {"title": "\uaf2c\ubbf8\ub2e4 <b>\ud669\uce58\uc988</b> \ud63c\ud569 <b>\ubd84\ub9d0 1kg</b>", "link": "https://search.shopping.naver.com/gate.nhn?id=38503721605", "image": "https://shopping-phinf.pstatic.net/main_3850372/38503721605.jpg", "lprice": "29900", "hprice": "", "mallName": "11\ubc88\uac00", "productId": "38503721605", "productType": "2", "brand": "", "maker": "", "category1": "\uc2dd\ud488", "category2": "\uac00\ub8e8/\ubd84\ub9d0\ub958", "category3": "\uae30\ud0c0\ubd84\ub9d0\uac00\ub8e8", "category4": ""}, {"title": "<b>\ud669\uce58\uc988 \ubd84\ub9d0</b> \uac00\ub9bc <b>1Kg</b> \uac00\ub8e8 \uc2dd\uc790\uc7ac \uc804\ubb38\uc810 \uc5c5\uc18c\uc6a9", "link": "https://search.shopping.naver.com/gate.nhn?id=38496800323", "image": "https://shopping-phinf.pstatic.net/main_3849680/38496800323.jpg", "lprice": "31910", "hprice": "", "mallName": "11\ubc88\uac00", "productId": "38496800323", "productType": "2", "brand": "", "maker": "", "category1": "\uc2dd\ud488", "category2": "\uac00\ub8e8/\ubd84\ub9d0\ub958", "category3": "\uae30\ud0c0\ubd84\ub9d0\uac00\ub8e8", "category4": ""}, {"title": "\uaf2c\ubbf8\ub2e4 <b>\ud669\uce58\uc988</b> \ud63c\ud569 <b>\ubd84\ub9d0 1kg</b>", "link": "https://search.shopping.naver.com/gate.nhn?id=38473148746", "image": "https://shopping-phinf.pstatic.net/main_3847314/38473148746.jpg", "lprice": "25970", "hprice": "", "mallName": "G\ub9c8\ucf13", "productId": "38473148746", "productType": "2", "brand": "", "maker": "", "category1": "\uc2dd\ud488", "category2": "\uac00\ub8e8/\ubd84\ub9d0\ub958", "category3": "\uae30\ud0c0\ubd84\ub9d0\uac00\ub8e8", "category4": ""}, {"title": "\uaf2c\ubbf8\ub2e4 <b>\ud669\uce58\uc988</b> \ud63c\ud569 <b>\ubd84\ub9d0 1kg</b>", "link": "https://search.shopping.naver.com/gate.nhn?id=38405925854", "image": "https://shopping-phinf.pstatic.net/main_3840592/38405925854.jpg", "lprice": "25960", "hprice": "", "mallName": "\uc625\uc158", "productId": "38405925854", "productType": "2", "brand": "", "maker": "", "category1": "\uc2dd\ud488", "category2": "\uac00\ub8e8/\ubd84\ub9d0\ub958", "category3": "\uae30\ud0c0\ubd84\ub9d0\uac00\ub8e8", "category4": ""}, {"title": "\uaf2c\ubbf8\ub2e4 <b>\ud669\uce58\uc988\ubd84\ub9d0</b>\uac00\ub8e8 <b>1kg</b>", "link": "https://search.shopping.naver.com/gate.nhn?id=38381604386", "image": "https://shopping-phinf.pstatic.net/main_3838160/38381604386.jpg", "lprice": "14000", "hprice": "", "mallName": "\ubca0\uc774\ud0b9\ub9d8", "productId": "38381604386", "productType": "2", "brand": "", "maker": "", "category1": "\uc2dd\ud488", "category2": "\uac00\ub8e8/\ubd84\ub9d0\ub958", "category3": "\uae30\ud0c0\ubd84\ub9d0\uac00\ub8e8", "category4": ""}, {"title": "\uc804\ubb38\uc810 \uc5c5\uc18c\uc6a9 <b>\ud669\uce58\uc988 \ubd84\ub9d0</b> \uac00\ub9bc <b>1Kg</b> \uac00\ub8e8 \uc2dd\uc790\uc7ac - Unbranded", "link": "https://search.shopping.naver.com/gate.nhn?id=38305312927", "image": "https://shopping-phinf.pstatic.net/main_3830531/38305312927.jpg", "lprice": "34800", "hprice": "", "mallName": "\ud2f0\ubaac", "productId": "38305312927", "productType": "2", "brand": "", "maker": "", "category1": "\uc2dd\ud488", "category2": "\uac00\ub8e8/\ubd84\ub9d0\ub958", "category3": "\uae30\ud0c0\ubd84\ub9d0\uac00\ub8e8", "category4": ""}, {"title": "\uc804\ubb38\uc810 \uc5c5\uc18c\uc6a9 <b>\ud669\uce58\uc988 \ubd84\ub9d0</b> \uac00\ub9bc <b>1Kg</b> \uac00\ub8e8 \uc2dd\uc790\uc7ac", "link": "https://search.shopping.naver.com/gate.nhn?id=38305959948", "image": "https://shopping-phinf.pstatic.net/main_3830595/38305959948.jpg", "lprice": "39700", "hprice": "", "mallName": "\uc625\uc158", "productId": "38305959948", "productType": "2", "brand": "", "maker": "", "category1": "\uc2dd\ud488", "category2": "\uac00\ub8e8/\ubd84\ub9d0\ub958", "category3": "\uae30\ud0c0\ubd84\ub9d0\uac00\ub8e8", "category4": ""}, {"title": "\uaf2c\ubbf8\ub2e4 <b>\ud669\uce58\uc988</b>\ud63c\ud569<b>\ubd84\ub9d0 1kg</b>", "link": "https://search.shopping.naver.com/gate.nhn?id=84124570028", "image": "https://shopping-phinf.pstatic.net/main_8412457/84124570028.jpg", "lprice": "17000", "hprice": "", "mallName": "\uc2f1\uc2f1\ucc44\uc18c \uadf8\ub9b0\ud31c", "productId": "84124570028", "productType": "2", "brand": "", "maker": "", "category1": "\uc2dd\ud488", "category2": "\uac00\ub8e8/\ubd84\ub9d0\ub958", "category3": "\uae30\ud0c0\ubd84\ub9d0\uac00\ub8e8", "category4": ""}, {"title": "\uaf2c\ubbf8\ub2e4 <b>\ud669\uce58\uc988</b> \ud63c\ud569 <b>\ubd84\ub9d0 1kg</b>", "link": "https://search.shopping.naver.com/gate.nhn?id=37959052301", "image": "https://shopping-phinf.pstatic.net/main_3795905/37959052301.jpg", "lprice": "30510", "hprice": "", "mallName": "\uc778\ud130\ud30c\ud06c\uc1fc\ud551", "productId": "37959052301", "productType": "2", "brand": "", "maker": "", "category1": "\uc2dd\ud488", "category2": "\uac00\ub8e8/\ubd84\ub9d0\ub958", "category3": "\uae30\ud0c0\ubd84\ub9d0\uac00\ub8e8", "category4": ""}, {"title": "\uc5c5\uc18c\uc6a9 <b>\ud669\uce58\uc988 \ubd84\ub9d0</b> \uac00\ub9bc <b>1Kg</b> \uac00\ub8e8 \uc2dd\uc790\uc7ac \uc804\ubb38\uc810", "link": "https://search.shopping.naver.com/gate.nhn?id=37847679128", "image": "https://shopping-phinf.pstatic.net/main_3784767/37847679128.jpg", "lprice": "22580", "hprice": "", "mallName": "\uc625\uc158", "productId": "37847679128", "productType": "2", "brand": "", "maker": "", "category1": "\uc2dd\ud488", "category2": "\uac00\ub8e8/\ubd84\ub9d0\ub958", "category3": "\uae30\ud0c0\ubd84\ub9d0\uac00\ub8e8", "category4": ""}, {"title": "\uc5c5\uc18c\uc6a9 <b>\ud669\uce58\uc988 \ubd84\ub9d0</b> \uac00\ub9bc <b>1Kg</b> \uac00\ub8e8 \uc2dd\uc790\uc7ac \uc804\ubb38\uc810", "link": "https://search.shopping.naver.com/gate.nhn?id=37846700520", "image": "https://shopping-phinf.pstatic.net/main_3784670/37846700520.jpg", "lprice": "22580", "hprice": "", "mallName": "G\ub9c8\ucf13", "productId": "37846700520", "productType": "2", "brand": "", "maker": "", "category1": "\uc2dd\ud488", "category2": "\uac00\ub8e8/\ubd84\ub9d0\ub958", "category3": "\uae30\ud0c0\ubd84\ub9d0\uac00\ub8e8", "category4": ""}, {"title": "\uc5c5\uc18c\uc6a9 <b>\ud669\uce58\uc988 \ubd84\ub9d0</b> \uac00\ub9bc <b>1Kg</b> \uac00\ub8e8 \uc2dd\uc790\uc7ac \uc804\ubb38\uc810", "link": "https://search.shopping.naver.com/gate.nhn?id=37846627810", "image": "https://shopping-phinf.pstatic.net/main_3784662/37846627810.jpg", "lprice": "27050", "hprice": "", "mallName": "\uc625\uc158", "productId": "37846627810", "productType": "2", "brand": "", "maker": "", "category1": "\uc2dd\ud488", "category2": "\uac00\ub8e8/\ubd84\ub9d0\ub958", "category3": "\uae30\ud0c0\ubd84\ub9d0\uac00\ub8e8", "category4": ""}, {"title": "\uc5c5\uc18c\uc6a9 <b>\ud669\uce58\uc988 \ubd84\ub9d0</b> \uac00\ub9bc <b>1Kg</b> \uac00\ub8e8 \uc2dd\uc790\uc7ac \uc804\ubb38\uc810", "link": "https://search.shopping.naver.com/gate.nhn?id=37827457230", "image": "https://shopping-phinf.pstatic.net/main_3782745/37827457230.jpg", "lprice": "23270", "hprice": "", "mallName": "G\ub9c8\ucf13", "productId": "37827457230", "productType": "2", "brand": "", "maker": "", "category1": "\uc2dd\ud488", "category2": "\uac00\ub8e8/\ubd84\ub9d0\ub958", "category3": "\uae30\ud0c0\ubd84\ub9d0\uac00\ub8e8", "category4": ""}, {"title": "[\uc81c\uacfc\uc81c\ube75 \uad6d\ub0b4\ubc30\uc1a1]<b>\ud669\uce58\uc988</b>\ub9db <b>\ubd84\ub9d0 1kg</b>", "link": "https://search.shopping.naver.com/gate.nhn?id=82874789782", "image": "https://shopping-phinf.pstatic.net/main_8287478/82874789782.jpg", "lprice": "14200", "hprice": "", "mallName": "\uc62c\ub9ac\ube44\uc544 \ubc14\uc2a4\ucf13", "productId": "82874789782", "productType": "2", "brand": "", "maker": "", "category1": "\uc2dd\ud488", "category2": "\uac00\ub8e8/\ubd84\ub9d0\ub958", "category3": "\uae30\ud0c0\ubd84\ub9d0\uac00\ub8e8", "category4": ""}, {"title": "\uac00\ub8e8<b>\ubd84\ub9d0</b> \uaf2c\ubbf8\ub2e4 <b>\ud669\uce58\uc988</b>\ud63c\ud569<b>\ubd84\ub9d0 1kg</b>", "link": "https://search.shopping.naver.com/gate.nhn?id=85345501003", "image": "https://shopping-phinf.pstatic.net/main_8534550/85345501003.jpg", "lprice": "30290", "hprice": "", "mallName": "\ud504\ub808\uc26c\ube4c\ub9ac\uc9c0", "productId": "85345501003", "productType": "2", "brand": "", "maker": "", "category1": "\uc2dd\ud488", "category2": "\uac00\ub8e8/\ubd84\ub9d0\ub958", "category3": "\uae30\ud0c0\ubd84\ub9d0\uac00\ub8e8", "category4": ""}, {"title": "<b>\ud669\uce58\uc988</b>\ud63c\ud569<b>\ubd84\ub9d0 1kg</b>/\uce58\uc988\uac00\ub8e8", "link": "https://search.shopping.naver.com/gate.nhn?id=28659532576", "image": "https://shopping-phinf.pstatic.net/main_2865953/28659532576.jpg", "lprice": "14500", "hprice": "", "mallName": "\ubca0\uc774\ud0b925", "productId": "28659532576", "productType": "2", "brand": "", "maker": "", "category1": "\uc2dd\ud488", "category2": "\uac00\ub8e8/\ubd84\ub9d0\ub958", "category3": "\uae30\ud0c0\ubd84\ub9d0\uac00\ub8e8", "category4": ""}, {"title": "\uac00\ub8e8<b>\ubd84\ub9d0</b> \uaf2c\ubbf8\ub2e4 <b>\ud669\uce58\uc988</b>\ud63c\ud569<b>\ubd84\ub9d0 1kg</b>", "link": "https://search.shopping.naver.com/gate.nhn?id=36101070240", "image": "https://shopping-phinf.pstatic.net/main_3610107/36101070240.jpg", "lprice": "31270", "hprice": "", "mallName": "\uc625\uc158", "productId": "36101070240", "productType": "2", "brand": "", "maker": "", "category1": "\uc2dd\ud488", "category2": "\uac00\ub8e8/\ubd84\ub9d0\ub958", "category3": "\uae30\ud0c0\ubd84\ub9d0\uac00\ub8e8", "category4": ""}, {"title": "\uac00\ub8e8<b>\ubd84\ub9d0</b> \uaf2c\ubbf8\ub2e4 <b>\ud669\uce58\uc988</b>\ud63c\ud569<b>\ubd84\ub9d0 1kg</b>", "link": "https://search.shopping.naver.com/gate.nhn?id=35836620514", "image": "https://shopping-phinf.pstatic.net/main_3583662/35836620514.jpg", "lprice": "20800", "hprice": "", "mallName": "\ub2e4\uc628\uc0c1\uc0ac", "productId": "35836620514", "productType": "2", "brand": "", "maker": "", "category1": "\uc2dd\ud488", "category2": "\uac00\ub8e8/\ubd84\ub9d0\ub958", "category3": "\uae30\ud0c0\ubd84\ub9d0\uac00\ub8e8", "category4": ""}, {"title": "\uac00\ub8e8<b>\ubd84\ub9d0</b> \uaf2c\ubbf8\ub2e4 <b>\ud669\uce58\uc988</b>\ud63c\ud569<b>\ubd84\ub9d0 1kg</b>", "link": "https://search.shopping.naver.com/gate.nhn?id=35800724544", "image": "https://shopping-phinf.pstatic.net/main_3580072/35800724544.jpg", "lprice": "34670", "hprice": "", "mallName": "G\ub9c8\ucf13", "productId": "35800724544", "productType": "2", "brand": "", "maker": "", "category1": "\uc2dd\ud488", "category2": "\uac00\ub8e8/\ubd84\ub9d0\ub958", "category3": "\uae30\ud0c0\ubd84\ub9d0\uac00\ub8e8", "category4": ""}]}